gflows/__init__.py
gflows/server.py
gflows/version.py
gflows/workflow.py
gflows/flows/__init__.py
gflows/flows/close_issues_in_column.py
gflows/flows/move_issues_on_commit.py
gflows/flows/share_labels_accross_repositories.py
gflows/flows/utils.py
gflows-1.0.0a8.dist-info/LICENSE.txt
gflows-1.0.0a8.dist-info/METADATA
gflows-1.0.0a8.dist-info/RECORD
gflows-1.0.0a8.dist-info/WHEEL
gflows-1.0.0a8.dist-info/top_level.txt
