Metadata-Version: 2.1
Name: gflows
Version: 1.0.0a8
Summary: GitHub workflow automation
Home-page: UNKNOWN
Author: tmbo
Author-email: tombocklisch@gmail.com
License: MIT
Project-URL: Bug Reports, https://github.com/tmbo/gflows/issues
Project-URL: Source, https://github.com/tmbo/gflows
Platform: UNKNOWN
Classifier: Programming Language :: Python :: 3.6
Requires-Dist: flask (~=1.0)
Requires-Dist: PyGithub (~=1.43)
